gg_release_notes/__init__.py
gg_release_notes/generate_release_notes.py
gg_release_notes/pull_request.py
gg_release_notes/upload.py
gg_release_notes/version.py
gg_release_notes/config/__init__.py
gg_release_notes/config/env_config.py
gg_release_notes/config/github_config.py
gg_release_notes/config/prompt_config.py
gg_release_notes/utils/__init__.py
gg_release_notes/utils/encode_bs64.py
gg_release_notes-1.7.1.dist-info/LICENSE
gg_release_notes-1.7.1.dist-info/METADATA
gg_release_notes-1.7.1.dist-info/WHEEL
gg_release_notes-1.7.1.dist-info/top_level.txt
gg_release_notes-1.7.1.dist-info/RECORD
