Metadata-Version: 2.1
Name: gg-release-notes
Version: 1.7.1
Summary: Python Interface for generating release notes for Github Actions
Home-page: https://github.com/DataWiz40/gg-release-notes/
Author: DataWiz40
License: UNKNOWN
Platform: UNKNOWN
Requires-Python: >=3.6
License-File: LICENSE
Requires-Dist: ghapi (==1.0.3)
Requires-Dist: openai (==1.16.0)
Requires-Dist: pydantic-settings (==2.2.1)
Requires-Dist: pydantic (==2.6.4)
Requires-Dist: python-dotenv (==0.21.0)
Requires-Dist: requests (==2.26.0)
Requires-Dist: slackclient (==2.9.4)
Provides-Extra: test
Requires-Dist: black (==23.1.0) ; extra == 'test'
Requires-Dist: pylint (==2.16.1) ; extra == 'test'
Requires-Dist: pytest (==6.2.5) ; extra == 'test'
Requires-Dist: twine ; extra == 'test'
Requires-Dist: wheel ; extra == 'test'
